smartdownsample/__init__.py
smartdownsample/core.py
smartdownsample-1.9.2.dist-info/licenses/LICENSE
smartdownsample-1.9.2.dist-info/METADATA
smartdownsample-1.9.2.dist-info/WHEEL
smartdownsample-1.9.2.dist-info/top_level.txt
smartdownsample-1.9.2.dist-info/RECORD
