Metadata-Version: 2.4
Name: smartdownsample
Version: 1.9.2
Summary: Smart image downsampling for image classification datasets
Author: Peter van Lunteren
License: MIT
Project-URL: Homepage, https://github.com/PetervanLunteren/smartdownsample
Project-URL: Repository, https://github.com/PetervanLunteren/smartdownsample
Project-URL: Issues, https://github.com/PetervanLunteren/smartdownsample/issues
Project-URL: Documentation, https://github.com/PetervanLunteren/smartdownsample#readme
Keywords: image,downsampling,camera-trap,machine-learning,computer-vision,diversity,deduplication
Classifier: Development Status :: 4 - Beta
Classifier: Intended Audience :: Science/Research
Classifier: License :: OSI Approved :: MIT License
Classifier: Operating System :: OS Independent
Classifier: Programming Language :: Python :: 3
Classifier: Programming Language :: Python :: 3.8
Classifier: Programming Language :: Python :: 3.9
Classifier: Programming Language :: Python :: 3.10
Classifier: Programming Language :: Python :: 3.11
Classifier: Programming Language :: Python :: 3.12
Classifier: Topic :: Scientific/Engineering :: Artificial Intelligence
Classifier: Topic :: Scientific/Engineering :: Image Processing
Classifier: Topic :: Software Development :: Libraries :: Python Modules
Requires-Python: >=3.8
License-File: LICENSE
Requires-Dist: numpy>=1.21.0
Requires-Dist: Pillow>=8.0.0
Requires-Dist: imagehash>=4.2.0
Requires-Dist: tqdm>=4.62.0
Requires-Dist: natsort>=8.0.0
Requires-Dist: matplotlib>=3.5.0
Requires-Dist: plotly>=5.0.0
Provides-Extra: dev
Requires-Dist: pytest>=6.0; extra == "dev"
Requires-Dist: black>=22.0; extra == "dev"
Requires-Dist: flake8>=4.0; extra == "dev"
Requires-Dist: mypy>=0.900; extra == "dev"
Dynamic: license-file
